{"response":[{"judet":"AB","data":"2022-03-05","judet_nume":"Alba","confirmed":51917,"incidence":6.23,"diff_confirmed":90},{"judet":"AR","data":"2022-03-05","judet_nume":"Arad","confirmed":66061,"incidence":6.43,"diff_confirmed":100},{"judet":"AG","data":"2022-03-05","judet_nume":"Argeș","confirmed":72538,"incidence":4.68,"diff_confirmed":78},{"judet":"BC","data":"2022-03-05","judet_nume":"Bacău","confirmed":59377,"incidence":2.02,"diff_confirmed":44},{"judet":"BH","data":"2022-03-05","judet_nume":"Bihor","confirmed":78913,"incidence":3.82,"diff_confirmed":62},{"judet":"BN","data":"2022-03-05","judet_nume":"Bistrița-Năsăud","confirmed":28992,"incidence":2.45,"diff_confirmed":35},{"judet":"BT","data":"2022-03-05","judet_nume":"Botoșani","confirmed":34875,"incidence":1.96,"diff_confirmed":38},{"judet":"BR","data":"2022-03-05","judet_nume":"Brăila","confirmed":30392,"incidence":3.92,"diff_confirmed":33},{"judet":"BV","data":"2022-03-05","judet_nume":"Brașov","confirmed":103694,"incidence":6.3,"diff_confirmed":135},{"judet":"B","data":"2022-03-05","judet_nume":"București","confirmed":515142,"incidence":16.77,"diff_confirmed":1614},{"judet":"BZ","data":"2022-03-05","judet_nume":"Buzău","confirmed":39098,"incidence":4.74,"diff_confirmed":74},{"judet":"CL","data":"2022-03-05","judet_nume":"Călărași","confirmed":24845,"incidence":3.31,"diff_confirmed":30},{"judet":"CS","data":"2022-03-05","judet_nume":"Caraș-Severin","confirmed":28838,"incidence":5.16,"diff_confirmed":67},{"judet":"CJ","data":"2022-03-05","judet_nume":"Cluj","confirmed":149984,"incidence":10.83,"diff_confirmed":446},{"judet":"CT","data":"2022-03-05","judet_nume":"Constanța","confirmed":111244,"incidence":6.61,"diff_confirmed":174},{"judet":"CV","data":"2022-03-05","judet_nume":"Covasna","confirmed":18888,"incidence":2.79,"diff_confirmed":28},{"judet":"DB","data":"2022-03-05","judet_nume":"Dâmbovița","confirmed":50363,"incidence":3.17,"diff_confirmed":55},{"judet":"DJ","data":"2022-03-05","judet_nume":"Dolj","confirmed":69078,"incidence":5.58,"diff_confirmed":163},{"judet":"GL","data":"2022-03-05","judet_nume":"Galați","confirmed":61195,"incidence":3.62,"diff_confirmed":167},{"judet":"GR","data":"2022-03-05","judet_nume":"Giurgiu","confirmed":27465,"incidence":4.68,"diff_confirmed":56},{"judet":"GJ","data":"2022-03-05","judet_nume":"Gorj","confirmed":21292,"incidence":2.2,"diff_confirmed":23},{"judet":"HR","data":"2022-03-05","judet_nume":"Harghita","confirmed":21047,"incidence":1.24,"diff_confirmed":17},{"judet":"HD","data":"2022-03-05","judet_nume":"Hunedoara","confirmed":55032,"incidence":5.77,"diff_confirmed":34},{"judet":"IL","data":"2022-03-05","judet_nume":"Ialomița","confirmed":26433,"incidence":4.02,"diff_confirmed":19},{"judet":"IS","data":"2022-03-05","judet_nume":"Iași","confirmed":106138,"incidence":4.08,"diff_confirmed":146},{"judet":"IF","data":"2022-03-05","judet_nume":"Ilfov","confirmed":114061,"incidence":11.44,"diff_confirmed":134},{"judet":"MM","data":"2022-03-05","judet_nume":"Maramureș","confirmed":48841,"incidence":1.96,"diff_confirmed":49},{"judet":"MH","data":"2022-03-05","judet_nume":"Mehedinți","confirmed":21059,"incidence":3.45,"diff_confirmed":43},{"judet":"MS","data":"2022-03-05","judet_nume":"Mureș","confirmed":60657,"incidence":5.1,"diff_confirmed":99},{"judet":"NT","data":"2022-03-05","judet_nume":"Neamț","confirmed":44636,"incidence":1.42,"diff_confirmed":34},{"judet":"OT","data":"2022-03-05","judet_nume":"Olt","confirmed":37369,"incidence":4.7,"diff_confirmed":75},{"judet":"PH","data":"2022-03-05","judet_nume":"Prahova","confirmed":94595,"incidence":6.37,"diff_confirmed":207},{"judet":"SJ","data":"2022-03-05","judet_nume":"Sălaj","confirmed":25832,"incidence":2.9,"diff_confirmed":21},{"judet":"SM","data":"2022-03-05","judet_nume":"Satu Mare","confirmed":31612,"incidence":1.67,"diff_confirmed":41},{"judet":"SB","data":"2022-03-05","judet_nume":"Sibiu","confirmed":74128,"incidence":9.01,"diff_confirmed":151},{"judet":"SV","data":"2022-03-05","judet_nume":"Suceava","confirmed":56864,"incidence":1.12,"diff_confirmed":40},{"judet":"TR","data":"2022-03-05","judet_nume":"Teleorman","confirmed":32765,"incidence":4.53,"diff_confirmed":79},{"judet":"TM","data":"2022-03-05","judet_nume":"Timiș","confirmed":142960,"incidence":8.49,"diff_confirmed":223},{"judet":"TL","data":"2022-03-05","judet_nume":"Tulcea","confirmed":20119,"incidence":1.79,"diff_confirmed":9},{"judet":"VL","data":"2022-03-05","judet_nume":"Vâlcea","confirmed":39658,"incidence":4.47,"diff_confirmed":48},{"judet":"VS","data":"2022-03-05","judet_nume":"Vaslui","confirmed":35402,"incidence":2.19,"diff_confirmed":51},{"judet":"VN","data":"2022-03-05","judet_nume":"Vrancea","confirmed":25464,"incidence":2.3,"diff_confirmed":44}],"count":42,"load_date":{"date":{"year":2022,"month":3,"day":6},"time":{"hour":7,"minute":44,"second":11,"nano":573961900}}}