{"response":[{"judet":"AB","data":"2022-02-18","judet_nume":"Alba","confirmed":49636,"incidence":17.92,"diff_confirmed":299},{"judet":"AR","data":"2022-02-18","judet_nume":"Arad","confirmed":63323,"incidence":18.76,"diff_confirmed":325},{"judet":"AG","data":"2022-02-18","judet_nume":"Argeș","confirmed":69552,"incidence":16.86,"diff_confirmed":458},{"judet":"BC","data":"2022-02-18","judet_nume":"Bacău","confirmed":57994,"incidence":6.09,"diff_confirmed":167},{"judet":"BH","data":"2022-02-18","judet_nume":"Bihor","confirmed":76803,"incidence":13.03,"diff_confirmed":277},{"judet":"BN","data":"2022-02-18","judet_nume":"Bistrița-Năsăud","confirmed":28153,"incidence":7.25,"diff_confirmed":136},{"judet":"BT","data":"2022-02-18","judet_nume":"Botoșani","confirmed":34075,"incidence":7.02,"diff_confirmed":115},{"judet":"BR","data":"2022-02-18","judet_nume":"Brăila","confirmed":29108,"incidence":8.89,"diff_confirmed":117},{"judet":"BV","data":"2022-02-18","judet_nume":"Brașov","confirmed":99587,"incidence":18.16,"diff_confirmed":686},{"judet":"B","data":"2022-02-18","judet_nume":"București","confirmed":478509,"incidence":35.44,"diff_confirmed":5217},{"judet":"BZ","data":"2022-02-18","judet_nume":"Buzău","confirmed":37081,"incidence":13.04,"diff_confirmed":309},{"judet":"CL","data":"2022-02-18","judet_nume":"Călărași","confirmed":23938,"incidence":9.56,"diff_confirmed":154},{"judet":"CS","data":"2022-02-18","judet_nume":"Caraș-Severin","confirmed":27277,"incidence":11.24,"diff_confirmed":225},{"judet":"CJ","data":"2022-02-18","judet_nume":"Cluj","confirmed":140918,"incidence":22.28,"diff_confirmed":1028},{"judet":"CT","data":"2022-02-18","judet_nume":"Constanța","confirmed":106715,"incidence":18.96,"diff_confirmed":676},{"judet":"CV","data":"2022-02-18","judet_nume":"Covasna","confirmed":17983,"incidence":8.41,"diff_confirmed":168},{"judet":"DB","data":"2022-02-18","judet_nume":"Dâmbovița","confirmed":48909,"incidence":10.35,"diff_confirmed":211},{"judet":"DJ","data":"2022-02-18","judet_nume":"Dolj","confirmed":65306,"incidence":14.05,"diff_confirmed":444},{"judet":"GL","data":"2022-02-18","judet_nume":"Galați","confirmed":58940,"incidence":9.33,"diff_confirmed":501},{"judet":"GR","data":"2022-02-18","judet_nume":"Giurgiu","confirmed":26117,"incidence":11.86,"diff_confirmed":190},{"judet":"GJ","data":"2022-02-18","judet_nume":"Gorj","confirmed":20542,"incidence":6.61,"diff_confirmed":91},{"judet":"HR","data":"2022-02-18","judet_nume":"Harghita","confirmed":20662,"incidence":5.08,"diff_confirmed":52},{"judet":"HD","data":"2022-02-18","judet_nume":"Hunedoara","confirmed":52624,"incidence":14.57,"diff_confirmed":432},{"judet":"IL","data":"2022-02-18","judet_nume":"Ialomița","confirmed":25371,"incidence":10.28,"diff_confirmed":150},{"judet":"IS","data":"2022-02-18","judet_nume":"Iași","confirmed":102137,"incidence":11.56,"diff_confirmed":462},{"judet":"IF","data":"2022-02-18","judet_nume":"Ilfov","confirmed":107894,"incidence":24.88,"diff_confirmed":855},{"judet":"MM","data":"2022-02-18","judet_nume":"Maramureș","confirmed":47922,"incidence":7.9,"diff_confirmed":158},{"judet":"MH","data":"2022-02-18","judet_nume":"Mehedinți","confirmed":20201,"incidence":8.48,"diff_confirmed":110},{"judet":"MS","data":"2022-02-18","judet_nume":"Mureș","confirmed":57820,"incidence":12.61,"diff_confirmed":371},{"judet":"NT","data":"2022-02-18","judet_nume":"Neamț","confirmed":43843,"incidence":5.83,"diff_confirmed":78},{"judet":"OT","data":"2022-02-18","judet_nume":"Olt","confirmed":35385,"incidence":12.26,"diff_confirmed":288},{"judet":"PH","data":"2022-02-18","judet_nume":"Prahova","confirmed":89926,"incidence":16.54,"diff_confirmed":613},{"judet":"SJ","data":"2022-02-18","judet_nume":"Sălaj","confirmed":25165,"incidence":9.17,"diff_confirmed":77},{"judet":"SM","data":"2022-02-18","judet_nume":"Satu Mare","confirmed":30946,"incidence":6.55,"diff_confirmed":77},{"judet":"SB","data":"2022-02-18","judet_nume":"Sibiu","confirmed":69287,"incidence":23.87,"diff_confirmed":767},{"judet":"SV","data":"2022-02-18","judet_nume":"Suceava","confirmed":56020,"incidence":3.93,"diff_confirmed":117},{"judet":"TR","data":"2022-02-18","judet_nume":"Teleorman","confirmed":31133,"incidence":8.67,"diff_confirmed":180},{"judet":"TM","data":"2022-02-18","judet_nume":"Timiș","confirmed":136829,"incidence":22.32,"diff_confirmed":770},{"judet":"TL","data":"2022-02-18","judet_nume":"Tulcea","confirmed":19729,"incidence":8.46,"diff_confirmed":50},{"judet":"VL","data":"2022-02-18","judet_nume":"Vâlcea","confirmed":37997,"incidence":13.23,"diff_confirmed":91},{"judet":"VS","data":"2022-02-18","judet_nume":"Vaslui","confirmed":34272,"incidence":5.63,"diff_confirmed":120},{"judet":"VN","data":"2022-02-18","judet_nume":"Vrancea","confirmed":24649,"incidence":6.79,"diff_confirmed":204}],"count":42,"load_date":{"date":{"year":2022,"month":2,"day":19},"time":{"hour":8,"minute":49,"second":32,"nano":774000000}}}